.hgignore
LICENSE
setup.py
LDB_LAPACK.egg-info/PKG-INFO
LDB_LAPACK.egg-info/SOURCES.txt
LDB_LAPACK.egg-info/dependency_links.txt
LDB_LAPACK.egg-info/namespace_packages.txt
LDB_LAPACK.egg-info/requires.txt
LDB_LAPACK.egg-info/top_level.txt
cffi/build_lapack.py
ldb/__init__.py
ldb/lapack/__init__.py
ldb/lapack/lapack.py
test/__init__.py
test/ldb/__init__.py
test/ldb/lapack/__init__.py
test/ldb/lapack/_lapack.py
test/ldb/lapack/lapack.py