Metadata-Version: 1.1
Name: LDB-LAPACK
Version: 0.1
Summary: A CFFI wrapper and helper functions/objects for LAPACK
Home-page: http://www.eldebe.org/ldb/lapack/
Author: Alex Orange
Author-email: alex@eldebe.org
License: AGPLv3
Platform: UNKNOWN
Classifier: Development Status :: 1 - Planning
Classifier: Intended Audience :: Developers
Classifier: Intended Audience :: Science/Research
Classifier: License :: OSI Approved :: GNU Affero General Public License v3
Classifier: Programming Language :: Python :: 2.7
Classifier: Programming Language :: Python :: Implementation :: CPython
Classifier: Programming Language :: Python :: Implementation :: PyPy
Classifier: Topic :: Scientific/Engineering :: Mathematics
